formic/LICENSE.txt
formic/VERSION.txt
formic/__init__.py
formic/command.py
formic/formic.py
formic/treewalk.py
formic2-1.0.3.dist-info/METADATA
formic2-1.0.3.dist-info/RECORD
formic2-1.0.3.dist-info/WHEEL
formic2-1.0.3.dist-info/entry_points.txt
formic2-1.0.3.dist-info/top_level.txt
