Metadata-Version: 2.1
Name: formic2
Version: 1.0.3
Summary: An implementation of Apache Ant FileSet and Globs
Home-page: https://github.com/wolfhong/formic
Author: Aviser LLP, Singapore; wolfhong
Author-email: hongxucai1991@gmail.com
License: GPLv3+
Keywords: Apache Ant,glob,recurse,FileSet,file utilities,find,fnmatcher
Platform: UNKNOWN
Classifier: License :: OSI Approved :: GNU General Public License v3 or later (GPLv3+)
Classifier: Programming Language :: Python
Classifier: Programming Language :: Python :: 2
Classifier: Programming Language :: Python :: 3
Classifier: Development Status :: 4 - Beta
Classifier: Intended Audience :: Developers
Classifier: Topic :: Software Development :: Libraries
Classifier: Topic :: Utilities
Requires-Python: >=2.6, <4
